<annotation>
	<folder>image</folder>
	<filename>data (252).jpg</filename>
	<path>C:\Users\12345\Desktop\111\專題資料夾\Data\image\data (252).jpg</path>
	<source>
		<database>Unknown</database>
	</source>
	<size>
		<width>4000</width>
		<height>3000</height>
		<depth>3</depth>
	</size>
	<segmented>0</segmented>
	<object>
		<name>car_card</name>
		<pose>Unspecified</pose>
		<truncated>0</truncated>
		<difficult>0</difficult>
		<bndbox>
			<xmin>1930</xmin>
			<ymin>1084</ymin>
			<xmax>2199</xmax>
			<ymax>1806</ymax>
		</bndbox>
	</object>
	<object>
		<name>car</name>
		<pose>Unspecified</pose>
		<truncated>0</truncated>
		<difficult>0</difficult>
		<bndbox>
			<xmin>725</xmin>
			<ymin>36</ymin>
			<xmax>3008</xmax>
			<ymax>2832</ymax>
		</bndbox>
	</object>
</annotation>
